st_table_words_icon/__init__.py
st_table_words_icon/frontend/build/asset-manifest.json
st_table_words_icon/frontend/build/bootstrap.min.css
st_table_words_icon/frontend/build/index.html
st_table_words_icon/frontend/build/lime.min.css
st_table_words_icon/frontend/build/style.css
st_table_words_icon/frontend/build/static/js/2.d03f8abe.chunk.js
st_table_words_icon/frontend/build/static/js/2.d03f8abe.chunk.js.LICENSE.txt
st_table_words_icon/frontend/build/static/js/2.d03f8abe.chunk.js.map
st_table_words_icon/frontend/build/static/js/main.5f334551.chunk.js
st_table_words_icon/frontend/build/static/js/main.5f334551.chunk.js.map
st_table_words_icon/frontend/build/static/js/runtime-main.83f9b806.js
st_table_words_icon/frontend/build/static/js/runtime-main.83f9b806.js.map
st_table_words_icon-0.0.9.dist-info/LICENSE
st_table_words_icon-0.0.9.dist-info/METADATA
st_table_words_icon-0.0.9.dist-info/WHEEL
st_table_words_icon-0.0.9.dist-info/top_level.txt
st_table_words_icon-0.0.9.dist-info/RECORD
