Metadata-Version: 2.1
Name: st-table-words-icon
Version: 0.0.9
Summary: Streamlit table sidebar with icon for click
Home-page: 
Author: Andell
Author-email: drogadvc@gmail.com
Requires-Python: >=3.7
License-File: LICENSE
Requires-Dist: streamlit >=0.63
